examples/__init__.py
examples/brain.py
examples/minion_model_adapter_example.py
examples/minion_with_smolagents_example.py
examples/smolagents_adapter.py
examples/tool_decorator_example.py
minion_manus/__init__.py
minion_manus/agent/__init__.py
minion_manus/agent/agent.py
minion_manus/config/__init__.py
minion_manus/config/settings.py
minion_manus/providers/__init__.py
minion_manus/providers/adapters.py
minion_manus/tools/__init__.py
minion_manus/tools/adapters.py
minion_manus/tools/base_tool.py
minion_manus/tools/browser_tool.py
minion_manus/tools/decorators.py
minion_manus/tools/default_tools.py
minion_manus/tools/tool_adapter.py
minion_manus/utils/__init__.py
minion_manus/utils/logging.py
minion_manus-0.1.0.dist-info/licenses/LICENSE
tests/__init__.py
tests/conftest.py
tests/test_basic_adapter.py
tests/test_minion_provider_adapter.py
tests/test_smolagents_integration.py
tests/test_smolagents_tools.py
tests/test_tool_functionality.py
minion_manus-0.1.0.dist-info/METADATA
minion_manus-0.1.0.dist-info/WHEEL
minion_manus-0.1.0.dist-info/top_level.txt
minion_manus-0.1.0.dist-info/RECORD
