Metadata-Version: 2.4
Name: minion-manus
Version: 0.1.0
Summary: A toolkit for implementing and managing tools for LLM agents
Home-page: https://github.com/femto/minion-manus
Author: FemtoZheng
Author-email: femto@example.com
Classifier: Programming Language :: Python :: 3
Classifier: Programming Language :: Python :: 3.8
Classifier: Programming Language :: Python :: 3.9
Classifier: Programming Language :: Python :: 3.10
Classifier: Programming Language :: Python :: 3.11
Classifier: License :: OSI Approved :: MIT License
Classifier: Operating System :: OS Independent
Classifier: Development Status :: 3 - Alpha
Classifier: Intended Audience :: Developers
Classifier: Topic :: Software Development :: Libraries :: Python Modules
Requires-Python: >=3.8
License-File: LICENSE
Requires-Dist: pydantic>=2.0.0
Requires-Dist: jsonschema>=4.0.0
Requires-Dist: typing-extensions>=4.0.0
Requires-Dist: aiohttp>=3.8.0
Requires-Dist: python-dotenv>=1.0.0
Requires-Dist: smolagents>=0.0.5
Requires-Dist: nest-asyncio>=1.5.6
Requires-Dist: sqlalchemy>=2.0.0
Requires-Dist: aiosqlite>=0.17.0
Provides-Extra: smolagents
Requires-Dist: smolagents>=0.0.5; extra == "smolagents"
Requires-Dist: nest-asyncio>=1.5.6; extra == "smolagents"
Provides-Extra: database
Requires-Dist: sqlalchemy>=2.0.0; extra == "database"
Requires-Dist: aiosqlite>=0.17.0; extra == "database"
Provides-Extra: dev
Requires-Dist: pytest>=7.0.0; extra == "dev"
Requires-Dist: pytest-asyncio>=0.21.0; extra == "dev"
Requires-Dist: black>=23.0.0; extra == "dev"
Dynamic: author
Dynamic: author-email
Dynamic: classifier
Dynamic: description
Dynamic: description-content-type
Dynamic: home-page
Dynamic: license-file
Dynamic: provides-extra
Dynamic: requires-dist
Dynamic: requires-python
Dynamic: summary
